.coveragerc
.isort.cfg
CHANGES.rst
CONTRIBUTORS.rst
LICENSE.rst
MANIFEST.in
README.rst
buildout.cfg
ci.cfg
requirements.txt
setup.py
versions.cfg
src/imio/__init__.py
src/imio.history.egg-info/PKG-INFO
src/imio.history.egg-info/SOURCES.txt
src/imio.history.egg-info/dependency_links.txt
src/imio.history.egg-info/entry_points.txt
src/imio.history.egg-info/namespace_packages.txt
src/imio.history.egg-info/not-zip-safe
src/imio.history.egg-info/requires.txt
src/imio.history.egg-info/top_level.txt
src/imio/history/__init__.py
src/imio/history/adapters.py
src/imio/history/config.py
src/imio/history/configure.zcml
src/imio/history/interfaces.py
src/imio/history/mk_sync_locales.sh
src/imio/history/safe_utils.py
src/imio/history/testing-adapter.zcml
src/imio/history/testing.py
src/imio/history/testing.zcml
src/imio/history/utils.py
src/imio/history/browser/__init__.py
src/imio/history/browser/configure.zcml
src/imio/history/browser/views.py
src/imio/history/browser/static/imiohistory.css
src/imio/history/browser/templates/content_history.pt
src/imio/history/browser/templates/document_byline.pt
src/imio/history/browser/templates/event_preview.pt
src/imio/history/browser/templates/header.pt
src/imio/history/browser/templates/version_preview.pt
src/imio/history/locales/imio.history.pot
src/imio/history/locales/manual.pot
src/imio/history/locales/plone.pot
src/imio/history/locales/en/LC_MESSAGES/imio.history.po
src/imio/history/locales/en/LC_MESSAGES/plone.po
src/imio/history/locales/es/LC_MESSAGES/imio.history.po
src/imio/history/locales/es/LC_MESSAGES/plone.po
src/imio/history/locales/fr/LC_MESSAGES/imio.history.po
src/imio/history/locales/fr/LC_MESSAGES/plone.po
src/imio/history/profiles/default/browserlayer.xml
src/imio/history/profiles/default/cssregistry.xml
src/imio/history/profiles/default/metadata.xml
src/imio/history/profiles/default/viewlets.xml
src/imio/history/profiles/testing/metadata.xml
src/imio/history/tests/__init__.py
src/imio/history/tests/adapters.py
src/imio/history/tests/test_contenthistory.py
src/imio/history/tests/test_documentbylineviewlet.py
src/imio/history/tests/test_revisionhistory.py
src/imio/history/tests/test_setup.py
src/imio/history/tests/test_utils.py
src/imio/history/tests/test_versionpreview.py
src/imio/history/tests/test_workflowhistory.py