Metadata-Version: 2.1
Name: imio.history
Version: 1.36
Summary: Imio history
Home-page: http://pypi.python.org/pypi/imio.history
Author: IMIO
Author-email: dev@imio.be
License: GPL
Keywords: Python Plone
Platform: UNKNOWN
Classifier: Development Status :: 6 - Mature
Classifier: Environment :: Web Environment
Classifier: Framework :: Plone
Classifier: Framework :: Plone :: 4.3
Classifier: License :: OSI Approved :: GNU General Public License v2 (GPLv2)
Classifier: Programming Language :: Python
Classifier: Programming Language :: Python :: 2.7
Provides-Extra: test
